README.md
pyproject.toml
setup.py
pyject/__init__.py
pyject/annotations.py
pyject/base.py
pyject/collections.py
pyject/conditions.py
pyject/container.py
pyject/exception.py
pyject/models.py
pyject/resolver.py
pyject/types.py
pyject/utils.py
pyjectt.egg-info/PKG-INFO
pyjectt.egg-info/SOURCES.txt
pyjectt.egg-info/dependency_links.txt
pyjectt.egg-info/not-zip-safe
pyjectt.egg-info/requires.txt
pyjectt.egg-info/top_level.txt