Metadata-Version: 2.1
Name: pyjectt
Version: 0.2.0
Summary: Light ioc container for you
Home-page: https://github.com/Bloodielie/pyject
Author: Bloodie_lie
Author-email: riopro2812@gmail.com
License: MIT License
Platform: UNKNOWN
Classifier: Environment :: Web Environment
Classifier: Topic :: Internet
Classifier: Programming Language :: Python :: 3
Classifier: Programming Language :: Python :: 3.7
Classifier: Programming Language :: Python :: 3.8
Classifier: Programming Language :: Python :: 3.9
Requires-Python: >=3.7
Provides-Extra: dev
